[
  {
    "name": "腾讯控股",
    "ticker": "0700.HK",
    "market": "港股",
    "aliases": ["Tencent"],
    "priority": "core",
    "mustCheck": true,
    "focusPoints": ["财报", "回购", "广告与游戏经营数据"],
    "officialSources": ["https://www.tencent.com"],
    "irSources": ["https://www.tencent.com/en-us/investors.html"],
    "exchangeSources": ["https://www.hkexnews.hk/"],
    "earningsSources": ["https://www.tencent.com/en-us/investors/financial-news.html"],
    "triggers": ["earnings", "buyback", "regulation"],
    "showOnCoveragePage": true,
    "publicSummary": "重点观察财报、回购、游戏与广告经营变化。",
    "publicFocusPoints": ["财报", "回购", "经营数据"],
    "sortOrder": 10
  },
  {
    "name": "阿里巴巴",
    "ticker": "9988.HK",
    "market": "港股",
    "aliases": ["Alibaba"],
    "priority": "core",
    "mustCheck": true,
    "focusPoints": ["电商与云业务", "资本分配", "回购"],
    "officialSources": ["https://www.alibabagroup.com"],
    "irSources": ["https://www.alibabagroup.com/en-US/ir-home"],
    "exchangeSources": ["https://www.hkexnews.hk/"],
    "earningsSources": ["https://www.alibabagroup.com/en-US/ir-financial-results"],
    "triggers": ["earnings", "buyback", "restructuring"],
    "showOnCoveragePage": true,
    "publicSummary": "重点观察电商、云与资本分配相关变化。",
    "publicFocusPoints": ["财报", "云业务", "回购"],
    "sortOrder": 20
  },
  {
    "name": "小米集团",
    "ticker": "1810.HK",
    "market": "港股",
    "aliases": ["Xiaomi"],
    "priority": "core",
    "mustCheck": true,
    "focusPoints": ["手机与 IoT 销量", "汽车业务进展", "利润率变化"],
    "officialSources": ["https://www.mi.com"],
    "irSources": ["https://ir.mi.com"],
    "exchangeSources": ["https://www.hkexnews.hk/"],
    "earningsSources": ["https://ir.mi.com/financial-information/quarterly-results"],
    "triggers": ["earnings", "product-launch", "sales"],
    "showOnCoveragePage": true,
    "publicSummary": "重点观察手机、IoT 与汽车业务推进，以及利润率变化。",
    "publicFocusPoints": ["财报", "汽车业务", "产品催化"],
    "sortOrder": 30
  },
  {
    "name": "英伟达",
    "ticker": "NVDA",
    "market": "美股",
    "aliases": ["NVIDIA"],
    "priority": "important",
    "mustCheck": false,
    "focusPoints": ["数据中心收入", "资本开支预期", "AI 芯片供需"],
    "officialSources": ["https://www.nvidia.com"],
    "irSources": ["https://investor.nvidia.com/"],
    "exchangeSources": ["https://www.sec.gov/"],
    "earningsSources": ["https://investor.nvidia.com/events-and-presentations/events-and-presentations/default.aspx"],
    "triggers": ["earnings", "guidance", "product-launch"],
    "showOnCoveragePage": true,
    "publicSummary": "重点观察数据中心收入、AI 芯片供需与资本开支信号。",
    "publicFocusPoints": ["财报", "指引", "产品催化"],
    "sortOrder": 40
  },
  {
    "name": "谷歌",
    "ticker": "GOOGL",
    "market": "美股",
    "aliases": ["Google", "Alphabet"],
    "priority": "important",
    "mustCheck": false,
    "focusPoints": ["云业务", "广告经营", "AI 产品进展"],
    "officialSources": ["https://abc.xyz"],
    "irSources": ["https://abc.xyz/investor/"],
    "exchangeSources": ["https://www.sec.gov/"],
    "earningsSources": ["https://abc.xyz/investor/earnings/"],
    "triggers": ["earnings", "product-launch", "conference"],
    "showOnCoveragePage": true,
    "publicSummary": "重点观察广告、云与 AI 产品推进相关变化。",
    "publicFocusPoints": ["财报", "云业务", "AI 产品"],
    "sortOrder": 50
  },
  {
    "name": "特斯拉",
    "ticker": "TSLA",
    "market": "美股",
    "aliases": ["Tesla"],
    "priority": "important",
    "mustCheck": false,
    "focusPoints": ["销量", "价格策略", "自动驾驶进展"],
    "officialSources": ["https://www.tesla.com"],
    "irSources": ["https://ir.tesla.com"],
    "exchangeSources": ["https://www.sec.gov/"],
    "earningsSources": ["https://ir.tesla.com/#quarterly-disclosure"],
    "triggers": ["sales", "earnings", "product-launch"],
    "showOnCoveragePage": true,
    "publicSummary": "重点观察销量、价格调整与自动驾驶业务进展。",
    "publicFocusPoints": ["销量", "财报", "自动驾驶"],
    "sortOrder": 60
  },
  {
    "name": "苹果",
    "ticker": "AAPL",
    "market": "美股",
    "aliases": ["Apple"],
    "priority": "important",
    "mustCheck": false,
    "focusPoints": ["硬件销量", "服务收入", "AI 功能进展"],
    "officialSources": ["https://www.apple.com"],
    "irSources": ["https://investor.apple.com"],
    "exchangeSources": ["https://www.sec.gov/"],
    "earningsSources": ["https://investor.apple.com/investor-relations/default.aspx"],
    "triggers": ["earnings", "product-launch", "conference"],
    "showOnCoveragePage": true,
    "publicSummary": "重点观察硬件销量、服务收入与 AI 功能推进。",
    "publicFocusPoints": ["财报", "服务业务", "AI 功能"],
    "sortOrder": 70
  },
  {
    "name": "中国平安",
    "ticker": "2318.HK",
    "market": "港股",
    "aliases": ["Ping An"],
    "priority": "event-driven",
    "mustCheck": false,
    "focusPoints": ["寿险新业务价值", "投资收益", "分红与资本管理"],
    "officialSources": ["https://group.pingan.com"],
    "irSources": ["https://group.pingan.com/investors/index.shtml"],
    "exchangeSources": ["https://www.hkexnews.hk/"],
    "earningsSources": ["https://group.pingan.com/investors/financial-reports/index.shtml"],
    "triggers": ["earnings", "dividend", "policy"],
    "showOnCoveragePage": true,
    "publicSummary": "重点观察寿险新业务价值、投资收益与资本分配变化。",
    "publicFocusPoints": ["财报", "分红", "保险经营"],
    "sortOrder": 80
  }
]
